pyedimax/__init__.py
pyedimax/smartplug.py
pyedimax-0.2.1.dist-info/LICENSE.md
pyedimax-0.2.1.dist-info/METADATA
pyedimax-0.2.1.dist-info/WHEEL
pyedimax-0.2.1.dist-info/top_level.txt
pyedimax-0.2.1.dist-info/RECORD
