Metadata-Version: 1.0
Name: pyedimax
Version: 0.2.1
Summary: Interface with Edimax Smart Plugs
Home-page: https://github.com/andreipop2005/pyedimax
Author: Andrei Pop
Author-email: andreipop2005@gmail.com
License: MIT
Platform: UNKNOWN
